Workbook

Sheet Instructions
A1: CFS Development Land Underwriting - CASE-3B Diagnostic Workbook
A3: Purpose | B3: Screening-level residual land-value context for CFS-PARCEL-0149758869. For review, not final pricing.
A4: Editable cells | B4: Yellow cells on Assumptions are editable assumptions. Green cells are formulas. Orange cells are warnings.
A5: Evidence labels | B5: CFS evidence, analyst benchmark, editable assumption, formula, professional estimate required, missing input.
A6: Limitations | B6: Not an appraisal, market value, fair value, recommended offer, investment advice, utility capacity confirmation, or entitlement approval.
A7: Safety | B7: No owner, mailing, restricted listing, raw score, exact probability, secret, or database credential data is included.

Sheet Parcel Evidence
A1: Parcel Evidence
A3: Field | B3: Evidence
A4: Parcel ID | B4: CFS-PARCEL-0149758869
A5: Gross acreage | B5: 489.43
A6: Preliminary developable-area screening estimate | B6: 392.11
A7: Screening score | B7: 89
A8: Planning context | B8: Concord; I-2 overlay requires planning interpretation and is not residential entitlement.
A9: Transportation context | B9: Road proximity evidence exists; legal access and off-site work are unconfirmed.
A10: Utility-readiness proxy | B10: Adjacent sewer-proximity and strong proxy; service availability and capacity are not confirmed.
A11: Environmental context | B11: Moderate mapped constraint band; FEMA/NWI overlap handled without double-counting.
A12: Evidence gaps | B12: Finished-lot comps, civil cost, utilities, entitlement, access, title/easements, survey, environmental/geotech.
A13: Source dates | B13: CASE-1 package 2026-07-18; benchmarks accessed 2026-07-20.

Sheet Assumptions
A1: Scenario Assumptions
A3: Input | B3: Downside | C3: Base | D3: Upside | E3: Unit | F3: Evidence Type | G3: Status
A4: Developable acreage | B4: 350 | C4: 392.11 | D4: 430 | E4: acres | F4: CFS evidence | G4: Needs Review
A5: Density | B5: 2.2 | C5: 2.8 | D5: 3.4 | E5: lots/dev acre | F5: Analyst benchmark | G5: Needs Review
A6: Estimated lots | B6: =B4*B5 -> 770 | C6: =C4*C5 -> 1097.908 | D6: =D4*D5 -> 1462 | E6: lots | F6: Formula | G6: Formula
A7: Finished-lot value | B7: 55000 | C7: 70000 | D7: 85000 | E7: $/lot | F7: Analyst benchmark | G7: Needs Review
A8: Internal horizontal cost per lot | B8: 85000 | C8: 70000 | D8: 60000 | E8: $/lot | F8: Analyst benchmark | G8: Professional estimate required
A9: Road/intersection allowance | B9: 15000000 | C9: 8000000 | D9: 4000000 | E9: $ | F9: Analyst allowance | G9: Professional estimate required
A10: Water-extension allowance | B10: 6000000 | C10: 3000000 | D10: 1500000 | E10: $ | F10: Analyst allowance | G10: Professional estimate required
A11: Sewer/special-utility allowance | B11: 10000000 | C11: 5000000 | D11: 2000000 | E11: $ | F11: CFS proxy + analyst allowance | G11: Professional estimate required
A12: Other off-site allowance | B12: 0 | C12: 0 | D12: 0 | E12: $ | F12: Missing input | G12: Blank until confirmed
A13: Soft-cost percentage | B13: 0.15 | C13: 0.12 | D13: 0.1 | E13: % hard costs | F13: Analyst assumption | G13: Needs Review
A14: Contingency percentage | B14: 0.2 | C14: 0.15 | D14: 0.1 | E14: % hard costs | F14: Analyst assumption | G14: Needs Review
A15: Selling-cost percentage | B15: 0.04 | C15: 0.03 | D15: 0.02 | E15: % revenue | F15: Analyst assumption | G15: Needs Review
A16: Financing/carry allowance | B16: 0.1 | C16: 0.08 | D16: 0.06 | E16: % costs | F16: Analyst assumption | G16: Needs Review
A17: Developer-margin percentage | B17: 0.18 | C17: 0.15 | D17: 0.12 | E17: % revenue | F17: Analyst assumption | G17: Needs Review
A18: Timeline | B18: 12 + 24 + 30 + 48 months | C18: 9 + 18 + 24 + 36 months | D18: 6 + 12 + 18 + 24 months | E18: text | F18: Analyst assumption | G18: Needs Review
A19: Scenario acquisition basis | E19: $ | F19: Missing input | G19: No asking price fabricated

Sheet Downside
A1: Downside Diagnostic Scenario
A3: Line item | B3: Value | C3: Notes
A4: Developable acres | B4: =Assumptions!B4 -> 350 | C4: Formula-driven diagnostic result.
A5: Density | B5: =Assumptions!B5 -> 2.2 | C5: Formula-driven diagnostic result.
A6: Estimated lots | B6: =B3*B4 -> 770 | C6: Formula-driven diagnostic result.
A7: Finished-lot value | B7: =Assumptions!B7 -> 55000 | C7: Formula-driven diagnostic result.
A8: Gross development revenue | B8: =B5*B6 -> 42350000 | C8: Formula-driven diagnostic result.
A9: Internal horizontal costs | B9: =B5*Assumptions!B8 -> 65450000 | C9: Formula-driven diagnostic result.
A10: Defined off-site costs | B10: =SUM(Assumptions!B9:B12) -> 31000000 | C10: Formula-driven diagnostic result.
A11: Modeled hard costs | B11: =B8+B9 -> 96450000 | C11: Formula-driven diagnostic result.
A12: Soft costs | B12: =B10*Assumptions!B13 -> 14467500 | C12: Formula-driven diagnostic result.
A13: Contingency | B13: =B10*Assumptions!B14 -> 19290000 | C13: Formula-driven diagnostic result.
A14: Selling costs | B14: =B7*Assumptions!B15 -> 1694000 | C14: Formula-driven diagnostic result.
A15: Financing/carry allowance | B15: =(B10+B11+B12)*Assumptions!B16 -> 13020750 | C15: Formula-driven diagnostic result.
A16: Required developer margin | B16: =B7*Assumptions!B17 -> 7623000 | C16: Formula-driven diagnostic result.
A17: Preliminary residual before land | B17: =B7-SUM(B8:B14) -> -110195250 | C17: Formula-driven diagnostic result.
A18: Supportable land-price status | B18: =IF(B15>0,"Preliminary maximum supportable land price","No positive supportable land price under current diagnostic assumptions") -> No positive supportable land price under current diagnostic assumptions | C18: Formula-driven diagnostic result.
A19: Key warning | B19: Screening priority does not equal financial feasibility.

Sheet Base
A1: Base Diagnostic Scenario
A3: Line item | B3: Value | C3: Notes
A4: Developable acres | B4: =Assumptions!C4 -> 392.11 | C4: Formula-driven diagnostic result.
A5: Density | B5: =Assumptions!C5 -> 2.8 | C5: Formula-driven diagnostic result.
A6: Estimated lots | B6: =B3*B4 -> 1097.908 | C6: Formula-driven diagnostic result.
A7: Finished-lot value | B7: =Assumptions!C7 -> 70000 | C7: Formula-driven diagnostic result.
A8: Gross development revenue | B8: =B5*B6 -> 76853560 | C8: Formula-driven diagnostic result.
A9: Internal horizontal costs | B9: =B5*Assumptions!C8 -> 76853560 | C9: Formula-driven diagnostic result.
A10: Defined off-site costs | B10: =SUM(Assumptions!C9:C12) -> 16000000 | C10: Formula-driven diagnostic result.
A11: Modeled hard costs | B11: =B8+B9 -> 92853560 | C11: Formula-driven diagnostic result.
A12: Soft costs | B12: =B10*Assumptions!C13 -> 11142427 | C12: Formula-driven diagnostic result.
A13: Contingency | B13: =B10*Assumptions!C14 -> 13928034 | C13: Formula-driven diagnostic result.
A14: Selling costs | B14: =B7*Assumptions!C15 -> 2305606.8 | C14: Formula-driven diagnostic result.
A15: Financing/carry allowance | B15: =(B10+B11+B12)*Assumptions!C16 -> 9433921.7 | C15: Formula-driven diagnostic result.
A16: Required developer margin | B16: =B7*Assumptions!C17 -> 11528034 | C16: Formula-driven diagnostic result.
A17: Preliminary residual before land | B17: =B7-SUM(B8:B14) -> -64338024 | C17: Formula-driven diagnostic result.
A18: Supportable land-price status | B18: =IF(B15>0,"Preliminary maximum supportable land price","No positive supportable land price under current diagnostic assumptions") -> No positive supportable land price under current diagnostic assumptions | C18: Formula-driven diagnostic result.
A19: Key warning | B19: Screening priority does not equal financial feasibility.

Sheet Upside
A1: Upside Diagnostic Scenario
A3: Line item | B3: Value | C3: Notes
A4: Developable acres | B4: =Assumptions!D4 -> 430 | C4: Formula-driven diagnostic result.
A5: Density | B5: =Assumptions!D5 -> 3.4 | C5: Formula-driven diagnostic result.
A6: Estimated lots | B6: =B3*B4 -> 1462 | C6: Formula-driven diagnostic result.
A7: Finished-lot value | B7: =Assumptions!D7 -> 85000 | C7: Formula-driven diagnostic result.
A8: Gross development revenue | B8: =B5*B6 -> 124270000 | C8: Formula-driven diagnostic result.
A9: Internal horizontal costs | B9: =B5*Assumptions!D8 -> 87720000 | C9: Formula-driven diagnostic result.
A10: Defined off-site costs | B10: =SUM(Assumptions!D9:D12) -> 7500000 | C10: Formula-driven diagnostic result.
A11: Modeled hard costs | B11: =B8+B9 -> 95220000 | C11: Formula-driven diagnostic result.
A12: Soft costs | B12: =B10*Assumptions!D13 -> 9522000 | C12: Formula-driven diagnostic result.
A13: Contingency | B13: =B10*Assumptions!D14 -> 9522000 | C13: Formula-driven diagnostic result.
A14: Selling costs | B14: =B7*Assumptions!D15 -> 2485400 | C14: Formula-driven diagnostic result.
A15: Financing/carry allowance | B15: =(B10+B11+B12)*Assumptions!D16 -> 6855840 | C15: Formula-driven diagnostic result.
A16: Required developer margin | B16: =B7*Assumptions!D17 -> 14912400 | C16: Formula-driven diagnostic result.
A17: Preliminary residual before land | B17: =B7-SUM(B8:B14) -> -14247640 | C17: Formula-driven diagnostic result.
A18: Supportable land-price status | B18: =IF(B15>0,"Preliminary maximum supportable land price","No positive supportable land price under current diagnostic assumptions") -> No positive supportable land price under current diagnostic assumptions | C18: Formula-driven diagnostic result.
A19: Key warning | B19: Screening priority does not equal financial feasibility.

Sheet Sens Value vs Cost
A1: Base sensitivity: finished-lot value vs horizontal cost per lot
A3: Value / Cost | B3: 50000 | C3: 60000 | D3: 70000 | E3: 80000 | F3: 90000
A4: 55000 | B4: -47724480 | C4: -62783386 | D4: -77842292 | E4: -92901198 | F4: -1.079601e+08
A5: 70000 | B5: -34220211 | C5: -49279118 | D5: -64338024 | E5: -79396930 | F5: -94455836
A6: 85000 | B6: -20715943 | C6: -35774849 | D6: -50833755 | E6: -65892661 | F6: -80951568
A7: 100000 | B7: -7211674.6 | C7: -22270581 | D7: -37329487 | E7: -52388393 | F7: -67447299
A8: 115000 | B8: 6292593.8 | C8: -8766312.4 | D8: -23825218 | E8: -38884125 | F8: -53943031

Sheet Sens Acres Density
A1: Base sensitivity: developable acreage vs modeled density
A3: Acres / Density | B3: 2.2 | C3: 2.6 | D3: 2.8 | E3: 3.2 | F3: 3.4
A4: 350 | B4: -51676840 | C4: -57082520 | D4: -59785360 | E4: -65191040 | F4: -67893880
A5: 375 | B5: -53800500 | C5: -59592300 | D5: -62488200 | E5: -68280000 | F5: -71175900
A6: 392.11 | B6: -55253933 | C6: -61309993 | D6: -64338024 | E6: -70394084 | F6: -73422114
A7: 410 | B7: -56773624 | C7: -63105992 | D7: -66272176 | E7: -72604544 | F7: -75770728
A8: 430 | B8: -58472552 | C8: -65113816 | D8: -68434448 | E8: -75075712 | F8: -78396344

Sheet Candidate Comparison
A1: Candidate | B1: Gross acres | C1: Developable estimate | D1: Score | E1: Decision | F1: Main advantage | G1: Main risk | H1: Financial status
A2: CFS-PARCEL-0149758869 | B2: 489.43 | C2: 392.11 | D2: 89 | E2: Targeted diligence only; do not advance to acquisition pricing yet | F2: Strongest physical/planning screen | G2: Financial scenarios negative | H2: No positive supportable land price under current diagnostic scenarios
A3: CFS-PARCEL-0149760035 | B3: 670.27 | C3: 554.36 | D3: 77 | E3: Retain for secondary review | F3: Largest developable estimate | G3: Infrastructure and entitlement questions unresolved | H3: Not underwritten
A4: CFS-PARCEL-0149777275 | B4: 233.26 | C4: 112.85 | D4: 36 | E4: Defer | F4: Meets acreage threshold | G4: Constraint and utility burden | H4: Not underwritten

Sheet Sources and Limitations
A1: Source | B1: Date | C1: Geography | D1: Metric | E1: Limitation | F1: Evidence type
A2: CFS CASE-1 package | B2: 2026-07-18 | C2: Cabarrus County | D2: Parcel evidence and scores | E2: Screening evidence only | F2: CFS-derived screening evidence
A3: CFS CASE-3A.1 benchmarks | B3: 2026-07-20 | C3: Cabarrus/Charlotte/National | D3: Market assumptions | E3: Indirect; professional study required | F3: Analyst benchmark
A4: Concord/WSACC fee schedules | B4: 2025-2027 | C4: Concord/Cabarrus | D4: Fee references | E4: Not utility capacity or extension estimate | F4: Confirmed public evidence
A5: NAHB benchmarks | B5: 2025-2026 | C5: United States/South Atlantic | D5: Lot share and lot values | E5: Not local finished-lot comps | F5: Analyst benchmark
A9: Verification requirement | B9: Civil, utility, transportation, planning, market, survey/title, environmental, geotechnical, and finance review required.
